{
    "songs": [
        {
            "id": "song_tera_chehra",
            "title": "Tera Chehra",
            "artist": "Arijit Singh",
            "film": "Sanam Teri Kasam",
            "details": "2016",
            "youtubeUrl": "https://www.youtube.com/watch?v=LOmC1dlZ2BE",
            "lyrics": [
                "(0:13 - 0:38): [#ff4444] मेरी बेचैनियों को चैन मिल जाए, तेरा चेहरा जब नज़र आए, तेरा चेहरा जब नज़र आए",
                "(0:39 - 0:58): [#ffaa00] मेरे दीवानेपन को सब्र मिल जाए, तेरा चेहरा जब नज़र आए, तेरा चेहरा जब नज़र आए",
                "(0:59 - 1:11): [#00ffcc] ज़िक्र तुम्हारा जब-जब होता है, देखो ना आँखों से भीगा-भीगा प्यार बह जाता है",
                "(1:12 - 1:35): [#cc00ff] मेरी तन्हाइयों को नूर मिल जाए, तेरा चेहरा जब नज़र आए, तेरा चेहरा जब नज़र आए",
                "(1:45 - 2:03): [#ff00ff] मैं रात-दिन ये दुआ करूँ, तेरे लिए मैं जियूँ-मरूँ, चारों पहर तुझे देखा करूँ, मेरा जहाँ ये तुझपे फ़ना करूँ",
                "(2:04 - 2:16): [#00ff00] ज़िक्र तुम्हारा जब-जब होता है, देखो ना होंठों पे तेरा एहसास रह जाता है",
                "(2:17 - 2:40): [#ff6600] मेरे हर रास्ते को मंज़िल मिल जाए, तेरा चेहरा जब नज़र आए, तेरा चेहरा जब नज़र आए",
                "(3:14 - 3:30): [#00aaff] बेरंग हवाएं मुझे ना जाने, दे गई सदा क्यों अभी-अभी, है सरफ़रोशी ये आशिक़ी भी, जाएगी जान मेरी इसमें कभी",
                "(3:31 - 3:45): [#ffcc00] ज़िक्र तुम्हारा जब-जब होता है, देखो ना हर लम्हा तेरी दास्ताँ कह जाता है",
                "(3:46 - 4:10): [#ff3399] मेरी हर इक तड़प को सुकून मिल जाए, तेरा चेहरा जब नज़र आए, तेरा चेहरा जब नज़र आए"
            ]
        },
        {
            "id": "dil_maang_raha_hai",
            "title": "Dil Maang Raha Hai",
            "artist": "Yasser Desai",
            "film": "Ghost",
            "details": "2019",
            "youtubeUrl": "https://youtu.be/3BHaD0MrrGE?si=MdmNlvN8FIIrJjAn",
            "lyrics": [
                "(0:32 - 0:46): [#ff4444] दिल मांग रहा है मोहलत तेरे साथ धड़कने की, तेरे नाम से जीने की, तेरे नाम से मरने की",
                "(0:47 - 0:54): [#ffaa00] दिल मांग रहा है मोहलत तेरे साथ धड़कने की, तेरे नाम से जीने की, तेरे नाम सुनने की",
                "(0:55 - 1:07): [#00ffcc] तेरे संग चलूं हरदम बन के परछाई, एक बारी इजाजत दे मुझे तुझ में ढलने की",
                "(1:32 - 1:41): [#ff00ff] देखा है जब से तुमको मैंने ये जाना है, मेरे ख्वाहिश के शहर में बस tera ठिकाना है",
                "(1:50 - 2:00): [#00ccff] मैं भूल गया खुद को भी बस याद रहा अब तू, आ तेरी हथेली पे इस दिल को मैं रख दूं",
                "(2:01 - 2:12): [#ff4444] दिल बोल रहा है हसरत हर हद से गुजरने की, तेरे नाम से जीने की, तेरे नाम से मरने की",
                "(2:13 - 2:22): [#ffaa00] दिल मांग रहा है मोहलत तेरे साथ धड़कने की, तेरे नाम से जीने की, तेरे नाम सुनने की",
                "(2:39 - 2:52): [#ccff00] दिल मांग रहा है मोहलत तेरे साथ धड़कने की, तेरे नाम से जीने की, तेरे नाम सुनने की"
            ]
        },
        {
            "id": "bol_kaffara_kya_hoga",
            "title": "Bol Kaffara Kya Hoga",
            "artist": "Neha Kakkar and Farhan Sabri",
            "film": "Bol Kaffara",
            "details": "2018",
            "youtubeUrl": "https://www.youtube.com/watch?v=kS1zP5YlTts",
            "lyrics": [
                "(0:23 - 0:34): [#FF5733] Saat pheron se bandha janmon ka ye bandhan, pyar se joda hai Rabb ne preet ka daaman",
                "(0:35 - 0:46): [#33FF57] Hai nayi rasmein, nayi kasmein, nayi uljhan, hont hai khamosh lekin keh rahi dhadkan",
                "(0:47 - 0:57): [#3357FF] Tere naam ke harf ki tasbeeh ko, saanson ke gale ka haar kiya, duniya bhooli aur sirf tujhe haan sirf tujhe hi pyar kiya",
                "(0:58 - 1:19): [#FF33A1] Tum jeet gaye hum hare, tum jeet gaye hum hare, hum hare aur tum jeete, mere dil ki dil se tauba, dil se tauba mere dil ki",
                "(1:20 - 1:35): [#F1C40F] Dil ki tauba hai dil ab pyar dobara na hoga, Bol kaffara kaffara, bol kaffara kaffara, bol o yaara o yaara, bol kaffara kya hoga",
                "(1:48 - 1:58): [#8E44AD] Humne dhadkan dhadkan karke, dil tere dil se jod liya, ankhon ne ankhen padh padh ke, tujhe vird bana ke yaad kiya",
                "(1:59 - 2:11): [#E67E22] Tujhe pyaar kiya toh tu hi bata, hum ne kya koi jurm kiya, aur jurm kiya hai toh bhi bata, ye jurm ki jurm ki kya hai sazaa",
                "(2:12 - 2:33): [#2ECC71] Tumhe hum se badh kar duniya, duniya tumhe humse badhkar, dil galti kar baitha hai, galti kar baitha hai dil, haaye dil galti kar baitha tu bol kaffara kya hoga",
                "(3:10 - 3:31): [#3498DB] Dil galti kar baitha hai, galti kar baitha hai dil, main kuch bhi kar lu, tum kabhi mujhse mohabbat nahi karna chahti, aur tum kuch bhi kar lo, main kabhi tumse nafrat nahi kar sakta",
                "(3:37 - 3:45): [#C0392B] Bol o yaara o yaara, bol kaffara kya hoga"
            ]
        },
        {
            "id": "song_tu_agar_meri",
            "title": "Tu Agar Meri",
            "artist": "Arijit Singh",
            "film": "Gehra Hua",
            "details": "2026",
            "youtubeUrl": "https://youtu.be/GVizJ_jpUnw",
            "lyrics": [
                "(0:21 - 0:25): [#00ffff] तू अगर मेरी ये हवाएं तेरी",
                "(0:26 - 0:30): [#00ffcc] तू अगर मेरी सारी राहें तेरी",
                "(0:31 - 0:35): [#ff00ff] तू अगर मेरी मैं हूं तेरा",
                "(0:36 - 0:40): [#ff0055] तू अगर मेरी ये उजाले तेरे",
                "(0:41 - 0:45): [#ffaa00] तू अगर मेरी दिल हवाले तेरे",
                "(0:46 - 0:50): [#00ff00] तू अगर मेरी मैं हूं तेरा",
                "(0:51 - 0:58): [#ffff00] बेताब सा मोहब्बत का तू इंकलाब है",
                "(0:59 - 1:05): [#a855f7] मेरा जहां तेरी बाहों में ख्वाब ख्वाब है",
                "(1:06 - 1:11): [#3b82f6] गहरा हुआ गहरा हुआ",
                "(1:12 - 1:17): [#ff0055] रंग आशिकी गहरा हुआ",
                "(1:18 - 1:23): [#00ffcc] गहरा हुआ गहरा हुआ",
                "(1:24 - 1:29): [#ff9900] दरिया दुआ गहरा हुआ",
                "(1:30 - 1:35): [#00ff00] तेरा हुआ",
                "(1:36 - 1:42): [#ff00ff] तू अगर मेरी ये हवाएं तेरी",
                "(1:43 - 1:49): [#00ffff] तू अगर मेरी सारी राहें तेरी",
                "(1:50 - 1:55): [#ffff00] तू अगर मेरी मैं हूं तेरा",
                "(2:08 - 2:12): [#00ffcc] पलकें झपकता है आसमान",
                "(2:13 - 2:17): [#ff0055] लाखों फरिश्तों की है तू जान",
                "(2:18 - 2:22): [#ffaa00] वो पूछते हैं रहती कहां",
                "(2:23 - 2:27): [#00ff00] मेरी बाहों में रहती उनको बता",
                "(2:28 - 2:32): [#ffff00] पलकें झपकती हैं आसमान",
                "(2:33 - 2:37): [#a855f7] उसने भी तुझसा देखा कहां",
                "(2:38 - 2:42): [#3b82f6] है रौनक वहां तू है जहां",
                "(2:43 - 2:47): [#ff5500] मेरी बाहों में रहना यही है दुआ",
                "(2:48 - 2:54): [#00ffff] तू अगर मेरी ये हवाएं तेरी",
                "(2:55 - 3:01): [#ff00ff] तू अगर मेरी सारी राहें तेरी",
                "(3:02 - 3:08): [#00ff00] तू agar मेरी मैं हूं तेरा",
                "(3:09 - 3:16): [#ff9900] बेताब सा मोहब्बत का तू इंकलाब है",
                "(3:17 - 3:23): [#00ffcc] मेरा जहां तेरी बाहों में ख्वाब ख्वाब है",
                "(3:24 - 3:29): [#ff0055] गहरा हुआ गहरा हुआ",
                "(3:30 - 3:34): [#ffff00] रंग आशिकी गहरा हुआ",
                "(3:35 - 3:39): [#a855f7] गहरा हुआ गहरा हुआ",
                "(3:40 - 3:45): [#3b82f6] दरिया दुआ गहरा हुआ, तेरा हुआ",
                "(3:46 - 3:55): [#00ff00] नी सा गा सा गा मा पा गा मा रे, नी सा गा सा गा मा पा गा रे सा",
                "(3:56 - 4:02): [#ff00ff] तेरी मोहब्बत में जलना भी है",
                "(4:03 - 4:09): [#00ffff] और तुझसे बचके ही चलना भी है",
                "(4:10 - 4:16): [#ffaa00] कुछ रंग अपना बदलना भी है",
                "(4:17 - 4:25): [#ffff00] मैंने ढलना तेरे रंग में है सदा",
                "(4:26 - 4:32): [#00ffcc] तू चांद है इक धड़कता हुआ",
                "(4:33 - 4:39): [#ff0055] चोरी से मुझको ही तकता हुआ",
                "(4:40 - 4:46): [#a855f7] सीने से लगके चमकता हुआ",
                "(4:47 - 4:55): [#00ff00] मेरी जन्नत का रास्ता तू ही तू हुआ",
                "(4:56 - 5:02): [#ff9900] तू अगर मेरी ये हवाएं तेरी",
                "(5:03 - 5:07): [#ff00ff] तू अगर मेरी सारी राहें तेरी",
                "(5:08 - 5:10): [#00ffff] तू अगर मेरी मैं हूं तेरा",
                "(5:11 - 5:17): [#ffff00] बेताब सा मोहब्बत का तू इंकलाब है",
                "(5:18 - 5:24): [#00ffcc] मेरा जहां तेरी बाहों में ख्वाब ख्वाब है",
                "(5:25 - 5:30): [#ff0055] गहरा हुआ गहरा हुआ",
                "(5:31 - 5:35): [#a855f7] रंग आशिकी गहरा हुआ",
                "(5:36 - 5:40): [#3b82f6] गहरा हुआ गहरा हुआ",
                "(5:41 - 5:46): [#ffaa00] दरिया दुआ गहरा हुआ."
            ]
        },
        {
            "id": "song_khairiyat",
            "title": "Khairiyat",
            "artist": "Arijit Singh",
            "film": "Chhichhore",
            "details": "2019",
            "youtubeUrl": "https://youtu.be/hoNb6HuNmU0?si=mBMAEEZsFrfBsJCo",
            "lyrics": [
                "(0:23 - 0:27): [#00ffff] खैरियत पूछो",
                "(0:27 - 0:30): [#00ffcc] कभी तो कैफियत पूछो",
                "(0:30 - 0:34): [#ff00ff] तुम्हारे बिन दीवाने का",
                "(0:34 - 0:37): [#ff9900] क्या हाल है",
                "(0:38 - 0:41): [#ff0055] दिल मेरा देखो",
                "(0:41 - 0:44): [#a855f7] ना मेरी हैसियत पूछो",
                "(0:44 - 0:47): [#00ff00] तेरे बिन एक दिन",
                "(0:47 - 0:50): [#00ffff] जैसे सौ साल है",
                "(0:52 - 0:55): [#ff00ff] अंजाम है तय मेरा",
                "(0:56 - 0:59): [#ff9900] होना तुम्हें है मेरा",
                "(1:00 - 1:03): [#ff0055] जितनी भी हो दूरियां",
                "(1:03 - 1:06): [#a855f7] फिलहाल हैं",
                "(1:09 - 1:14): [#00ffcc] ये दूरियां फिलहाल हैं",
                "(1:15 - 1:19): [#00ffff] ओ खैरियत पूछो",
                "(1:19 - 1:22): [#00ffcc] कभी तो कैफियत पूछो",
                "(1:23 - 1:26): [#ff00ff] तुम्हारे बिन दीवाने का",
                "(1:26 - 1:30): [#ff9900] क्या हाल है",
                "(1:32 - 1:35): [#ff0055] दिल मेरा देखो",
                "(1:35 - 1:38): [#a855f7] ना मेरी हैसियत पूछो",
                "(1:38 - 1:41): [#00ff00] तेरे बिन एक दिन",
                "(1:41 - 1:44): [#00ffff] जैसे सौ साल है",
                "(1:56 - 2:00): [#ff00ff] तुम्हारी तस्वीर के सहारे",
                "(2:00 - 2:03): [#ff9900] मौसम कई गुजारे",
                "(2:04 - 2:08): [#ff0055] मौसमी ना समझो",
                "(2:08 - 2:11): [#a855f7] पर इश्क को हमारे",
                "(2:12 - 2:16): [#00ff00] नजरों के सामने मैं",
                "(2:16 - 2:19): [#00ffff] आता नहीं तुम्हारे",
                "(2:19 - 2:23): [#00ffcc] मगर रहते हो हर पल",
                "(2:23 - 2:26): [#ff00ff] मंजर में तुम हमारे",
                "(2:27 - 2:30): [#ff9900] अगर इश्क से है मिला",
                "(2:30 - 2:33): [#ff0055] फिर दर्द से क्या गिला",
                "(2:33 - 2:36): [#a855f7] इस दर्द में जिंदगी",
                "(2:36 - 2:39): [#00ff00] खुशहाल है",
                "(2:43 - 2:47): [#00ffff] ये दूरियां फिलहाल हैं",
                "(2:49 - 2:53): [#00ffcc] ओ खैरियत पूछो",
                "(2:53 - 2:56): [#ff00ff] कभी तो कैफियत पूछो",
                "(2:56 - 3:00): [#ff9900] तुम्हारे बिन दीवाने का",
                "(3:00 - 3:03): [#ff0055] क्या हाल है",
                "(3:06 - 3:09): [#a855f7] दिल मेरा देखो",
                "(3:09 - 3:12): [#00ff00] ना मेरी हैसियत पूछो",
                "(3:12 - 3:15): [#00ffff] तेरे बिन एक दिन",
                "(3:15 - 3:18): [#00ffcc] जैसे सौ साल है",
                "(3:20 - 3:23): [#ff00ff] अंजाम है तय मेरा",
                "(3:23 - 3:26): [#ff9900] होना तुम्हें है मेरा",
                "(3:26 - 3:29): [#ff0055] जितनी भी हो दूरियां",
                "(3:29 - 3:32): [#a855f7] फिलहाल हैं",
                "(3:37 - 3:41): [#00ff00] ये दूरियां फिलहाल हैं"
            ]
        },
        {
            "id": "song_ruposh_ost",
            "title": "Ruposh",
            "artist": "Wajhi Farooki",
            "film": "Ruposh OST",
            "details": "2021",
            "youtubeUrl": "https://www.youtube.com/watch?v=kYJ-l-a_R4Y",
            "lyrics": [
                "(0:27 - 0:47): [#ff4444] जिंदगी के gam भुलाकर चलता रहा, मुश्किलों से मुस्कुरा कर बढ़ता रहा",
                "(0:52 - 1:07): [#00ffcc] तू मिल गई तो लगा जैसे कितनी ही बेरू थी जिंदगी, पल पल खुदा से tera इश्क मांगा दुआ क्यों हुई अनसुनी",
                "(1:10 - 1:28): [#ffaa00] हमने बांधा है तेरे इश्क में अहराम-ए-जुनून, हम भी देखेंगे तमाशा तेरी लैला का",
                "(1:28 - 1:46): [#ff00ff] होके रूपोश, रूपोश, रूपोश, होके रूपोश ना दिल तोड़ तमन्ना का, होके रूपोश",
                "(1:56 - 2:10): [#44ff44] तेरी नज़रों के सदके, यह जान वार दूंगा, तू जो कह दे तो अपना जहां वार दूंगा",
                "(2:10 - 2:24): [#ffff00] मैंने मौला से तेरी मेरी दुनिया है मांगी, तू जो लिख दे तो उसको ही हक मान लूंगा",
                "(2:24 - 2:49): [#ff8800] दुनिया भुला के मैंने तुझको है पा लिया, दिल से दुआओं में भी तुझको ही मांगा, रूह का गुरूर सारा तुझ पे लुटा दिया, खुद को हरा के तेरी जीत को ही मांगा, वाकिफ है जहां के रिवाजों से मैं नजरों से तेरी हर नजर उतारूं",
                "(2:55 - 3:18): [#0088ff] हमने बांधा है तेरे इश्क में अहराम-ए-जुनून, हम भी देखेंगे तमाशा तेरी लैला का, होके रूपोश, रूपोश, रूपोश",
                "(3:59 - 4:10): [#ff44aa] तेरी नजरों के सदके, जान वार दूंगा, तू जो कह दे तो अपना जहां वार दूंगा"
            ]
        },
        {
            "id": "gehra_hua_dhurandhar",
            "title": "Gehra Hua",
            "artist": "Arijit Singh, Armaan Khan",
            "film": "Gehra Hua",
            "details": "2026",
            "youtubeUrl": "https://www.youtube.com/watch?v=F3a37y1D-qU",
            "lyrics": [
                "(0:21 - 0:35): [#FF5733] तू अगर मेरी ये हवाएं तेरी, तू अगर मेरी सारी राहें तेरी, तू अगर मेरी मैं हूं तेरा",
                "(0:36 - 0:50): [#33FF57] तू अगर मेरी ये उजाले तेरे, तू अगर मेरी दिल हवाले तेरे, तू अगर मेरी मैं हूं तेरा",
                "(0:51 - 1:05): [#3357FF] बेताब सा मोहब्बत का तू इंकलाब है, मेरा जहां तेरी बाहों में ख्वाब ख्वाब है",
                "(1:06 - 1:35): [#F333FF] गहरा हुआ, गहरा हुआ, रंग आशिकी, गहरा हुआ, गहरा हुआ, गहरा हुआ, दरिया दुआ, गहरा हुआ, तेरा हुआ",
                "(2:08 - 2:27): [#FF33A8] पलकें झपकता है आसमान, लाखों फरिश्तों की है तू जान, वो पूछते हैं रहती कहां, मेरी बाहों में रहती उनको बता",
                "(2:28 - 2:47): [#A8FF33] पलकें झपकता है आसमान, उसने भी तुझ सा देखा कहां, है रौनकें वहां तू है जहां, मेरी बाहों में रहना यही है दुआ",
                "(2:48 - 3:08): [#FF8C33] तू अगर मेरी है फसाना तेरा, तू अगर मेरी तो जमाना तेरा, तू अगर मेरी मैं हूं तेरा, बेताब सा मोहब्बत का तू इंकलाब है, मेरा जहां तेरी बाहों में ख्वाब ख्वाब है",
                "(3:41 - 3:55): [#33FFF6] नी सा गा सा गा मा पा गा मा रे, नी सा गा सा गा मा पा गा रे सा",
                "(3:56 - 4:26): [#D433FF] तेरी मोहब्बत में जलना भी है, और तुझसे बच के ही चलना भी है, कुछ रंग अपना बदलना भी है, मैंने ढलना तेरे रंग में है सदा, तू चांद है इक धड़कता हुआ, चोरी से मुझको ही तकता हुआ, सीने से लग के चमकता हुआ, मेरी जन्नत का रस्ता तू ही तो हुआ",
                "(4:27 - 5:28): [#FF3333] तू अगर मेरी ये हवाएं तेरी, तू अगर मेरी सारी राहें तेरी, तू अगर मेरी मैं हूं तेरा, बेताब सा मोहब्बत का तू इंकलाब है, मेरा जहां तेरी बाहों में ख्वाब ख्वाब है, गहरा हुआ, गहरा हुआ, रंग आशिकी, गहरा हुआ, गहरा हुआ, गहरा हुआ, दरिया दुआ, गहरा हुआ"
            ]
        },
        {
            "id": "aawaara_angaara_tere_ishk_mein",
            "title": "Aawaara Angaara",
            "artist": "Faheem Abdullah",
            "film": "Aawaara Angaara",
            "details": "2024",
            "youtubeUrl": "https://www.youtube.com/watch?v=kYx-Rz3zJ24",
            "lyrics": [
                "(0:40 - 0:52): [#FF5733] तेरी कायनात मेरे खाली हाथ और तारतार सपने",
                "(0:52 - 1:05): [#33FF57] तेरी कायनात मेरे खाली हाथ और तारतार सपने, दर्दों से चूर gam का गुरूर कहूं क्या मैं हाल अपने",
                "(1:05 - 1:26): [#3357FF] आवारा रातों में डूबा अंबर का बंजारा",
                "(1:29 - 1:42): [#F333FF] जाने टूटा क्यों मैं शीशा ना तारा",
                "(1:42 - 1:57): [#FF3385] तेरी कायनात मेरे खाली हाथ और तारतार सपने, गए जख्म जाग मेरे सीने आग लगी सांसे सांस तपने",
                "(2:13 - 2:26): [#FFC300] कोई उधारी है सीने पे भारी है, पत्थर है या दिल है मैं ही अकेला हूं मैं ही तो मेला हूं ये कैसी महफिल है",
                "(2:26 - 2:37): [#DAF7A6] रूठे सवेरे हैं आधे ही मेरे हैं आधे हैं ये तेरे, निगाहों में लवा है आंखों में बस सर्द शाम गहरे",
                "(2:37 - 3:00): [#581845] आवारा आवारा आवारा आंसू है मेरे या पिघला है पारा",
                "(3:03 - 3:12): [#900C3F] जाने टूटा क्यों मैं शीशा ना तारा",
                "(3:41 - 4:03): [#C70039] मेरा इम्तिहान तू जो ले रहा है अब ना रियायत कर",
                "(4:44 - 5:01): [#FF5733] मेरा इम्तहान तू जो ले रहा है अब ना रियायत कर, मैंने इश्क सीखा मैंने प्यार सीखा तू चाहे नफरत कर"
            ]
        },
        {
            "id": "song_lutt_le_gaya",
            "title": "Lutt Le Gaya",
            "artist": "Simran Choudhary",
            "film": "Lutt Le Gaya",
            "details": "2023",
            "youtubeUrl": "https://www.youtube.com/watch?v=vx9-SmQ2wuQ",
            "lyrics": [
                "(0:08 - 0:25): [#ff4444] आजा वे आजा, आजा वे आजा, हाय सजन, आजा वे आजा, आजा वे आजा, सीने लाजा, हाय सजन",
                "(0:26 - 0:45): [#ffaa00] मेनू लुट ले गया, हाय हाय सजन मेनू लुट ले गया, प्यासे लबां ते रोग मुका जा, हाय सजन मेनू लुट ले गया",
                "(0:46 - 1:10): [#00ffcc] हाय हाय सजन मेनू लुट ले गया, हाय सजन मेरी अक्खियां तरस दी, हाय ईमान मेरा तुट पै गया, मेनू लुट ले गया",
                "(1:11 - 1:30): [#ccff00] ओ मेनू लुट ले गया, ओ मेनू लुट ले गया, ओ मेनू लुट ले गया, आजा वे आजा, ओ मेनू लुट ले गया, आजा वे आजा",
                "(2:10 - 2:30): [#ff00ff] तपदी अक्खियां, अज ना मुकियां, नैना विच तू वस्स गया, रज्ज के पीवां तैनू सजना, रातां विच आ रस्स गया",
                "(2:31 - 2:50): [#0088ff] हाय वसना चानवा विच मैं सानवां, मेनू ओ फिर खींच पुट ले गया, हाय सजन मेरी अक्खियां तरस दी",
                "(2:51 - 3:20): [#ff6600] हाय ईमान मेरा तुट पै गया, मेनू लुट ले गया, ओ मेनू लुट ले गया, ओ मेनू लुट ले गया, ओ मेनू लुट ले गया, ओ मेनू लुट ले गया",
                "(3:21 - 4:18): [#9900ff] आजा वे आजा, आजा वे आजा, आजा वे आजा, आजा वे आजा, हाय सजन, हाय सजन"
            ]
        },
        {
            "id": "song_bekhayali",
            "title": "Bekhayali",
            "artist": "Sachet Tandon",
            "film": "Kabir Singh",
            "details": "2019",
            "youtubeUrl": "https://www.youtube.com/watch?v=Ye8mB6V_INQ",
            "lyrics": [
                "(0:29 - 0:44): [#ff4444] Bekhayali mein bhi tera hi khayaal aaye, Kyun bichhadna hai zaroori ye sawaal aaye",
                "(0:45 - 1:00): [#ffaa00] Teri nazdeekiyon ki khushi behisaab thi, Hissay mein faasle bhi tere bemisaal aaye",
                "(1:02 - 1:16): [#ffcc00] Main jo tujhse door hoon, Kyun door main rahoon, Tera guroor hoon, Tu faasla mita, Tu khwaab sa mila, Kyun khwaab tod doon",
                "(1:36 - 1:51): [#ff4444] Bekhayali mein bhi tera hi khayaal aaye, Kyun bichhadna hai zaroori ye sawaal aaye",
                "(1:52 - 2:06): [#ff6699] Thoda sa main khafa ho gaya apne aap se, Thoda sa tujh pe bhi bewajah malaal aaye",
                "(2:20 - 2:34): [#cc00ff] Haye ye tadpan hai, Ye uljhan hai, Kaise jee loon bina tere, Meri ab sabse hai anban, Bante kyun ye khuda mere",
                "(2:53 - 3:07): [#33ccff] Ye jo log-baag hain, Jungle ki aag hain, Kyun aag mein jaloon, Ye nakaam pyaar mein, Khush hai ye haar mein, In jaisa kyun banoon",
                "(3:37 - 3:54): [#00ffcc] Raatein dengi bata, Neendhon mein teri hi baat hai, Bhooloon kaise tujhe, Tu toh khayalon mein saath hai",
                "(3:54 - 4:05): [#ff4444] Bekhayali mein bhi tera hi khayaal aaye, Kyun bichhadna hai zaroori ye sawaal aaye",
                "(4:28 - 4:44): [#9933ff] Nazron ke aage har ek manzar, Ret ki tarah bikhar raha hai, Dard tumhara hai, Badan mein mere zehar ki tarah utar raha hai",
                "(5:05 - 5:24): [#ff9966] Aamane, Aamane, Rooth-ta nahi, Faaslon se faasla, Ye toot-ta nahi",
                "(5:25 - 5:44): [#ff3300] Na hai woh bewafa, Aur na main hoon bewafa, Woh meri aadaton ki tarah, Chhoot-ta nahi"
            ]
        },
        {
            "id": "kaun_tujhe",
            "title": "Kaun Tujhe",
            "artist": "Palak Muchhal",
            "film": "M.S. Dhoni - The Untold Story",
            "details": "2016",
            "youtubeUrl": "https://www.youtube.com/watch?v=atEn-n03Z0w",
            "lyrics": [
                "[0:18] [#FF5733] Tu aata hai seene mein jab jab saansein bharti hoon",
                "[0:27] [#FF5733] Tere dil ki galiyon se main har roz guzarti hoon",
                "[0:33] [#FFC300] Hawa ke jaise chalta hai tu main ret jaise udti hoon",
                "[0:40] [#DAF7A6] Kaun tujhe yoon pyaar karega jaise main karti hoon",
                "[1:29] [#C70039] Meri nazar ka safar tujh pe hi aake ruke",
                "[1:38] [#C70039] Kehne ko baaki hai kya kehna tha jo keh chuke",
                "[1:46] [#900C3F] Meri nigaahein hai teri nigaahon ki tujhe khabar kya bekhabar",
                "[1:55] [#581845] Main tujhse hi chhup chhup kar teri aankhein padhti hoon",
                "[2:03] [#FF5733] Kaun tujhe yoon pyaar karega jaise main karti hoon",
                "[2:53] [#33FF57] Tu jo mujhe aa mila sapne hue sarphire",
                "[2:58] [#33FF57] Haathon mein aate nahin udte hain lamhe mere",
                "[3:06] [#33C1FF] Meri hansi tujhse meri khushi tujhse tujhe khabar kya beqadar",
                "[3:16] [#FF33A1] Jis din tujhko na dekhun paagal paagal phirti hoon",
                "[3:24] [#FF5733] Kaun tujhe yoon pyaar karega jaise main karti hoon"
            ]
        },
        {
            "id": "andaaz_e_karam_madhur_sharma",
            "title": "Andaaz e Karam",
            "artist": "Madhur Sharma",
            "film": "Andaaz e Karam",
            "details": "Madhur Sharma Cover",
            "youtubeUrl": "https://www.youtube.com/watch?v=J5-v9S40yvM",
            "lyrics": [
                "(0:37 - 1:09): [#ff4444] ना सुना उसने तवज्जो से फसाना दिल का, उम्र गुजरी है मगर दर्द ना जाना दिल का",
                "(1:20 - 1:43): [#ffaa00] उनके अंदाज-ए-करम उनपे वो आना दिल का, उनके अंदाज-ए-करम उनपे वो आना दिल का",
                "(1:48 - 2:20): [#00ffcc] दिल के टुकड़े जो किए थे ना मंजर पूछो, तोड़ के दिल को मेरे किया बहाना दिल का",
                "(2:32 - 2:55): [#ff00ff] उनके अंदाज-ए-करम उनपे वो आना दिल का, उनके अंदाज-ए-करम उनपे वो आना दिल का",
                "(3:22 - 3:55): [#44ff44] करके मायूस मेरे दिल को मिला क्या उनको, भूल ना पाए कभी टूट वो जाना दिल का",
                "(4:06 - 4:18): [#4444ff] उनके अंदाज-ए-करम उनपे वो आया दिल का",
                "(4:23 - 4:55): [#ff44ff] मैं बरसों से गिला ना है ना शिकवा कोई, पी के तू नहीं लिया निशाना दिल का",
                "(5:06 - 5:29): [#00ffff] उनके अंदाज-ए-करम उनपे वो आता दिल का, उनके अंदाज-ए-करम उनपे वो आया दिल का",
                "(5:54 - 6:26): [#ff8800] वो भी अपने ना हुए दिल भी गया हाथों से, आने से तो है ना आना दिल का ऐसे तू है"
            ]
        },
        {
            "id": "agar_tum_saath_ho_tamasha",
            "title": "Agar Tum Saath Ho",
            "artist": "Alka Yagnik, Arijit Singh",
            "film": "Tamasha",
            "details": "2015 Original Soundtrack",
            "youtubeUrl": "https://www.youtube.com/watch?v=XW8i3P9yQ3E",
            "lyrics": [
                "(0:14 - 0:30): [#ff4444] Humne duniya ki chamak dekh ke jaana aakhir, dil ka sukoon hi sabse bada rehta hai.",
                "(0:35 - 0:47): [#00ffcc] Dil ka sukoon hi sabse bada rehta hai, phool khushboo se juda ho nahi sakte hargiz.",
                "(0:53 - 1:06): [#ffaa00] Ishq ki rag mein wafa banke rawa rehta hai.",
                "(1:14 - 1:30): [#ff00ff] Raat khamosh thi lekin mere andar har su, ek sada banke ummeedon ka diya rehta hai.",
                "(1:44 - 2:06): [#44ff44] Phool khushboo se juda ho nahi sakte hargiz, ishq ki rag mein wafa banke rawa rehta hai.",
                "(2:14 - 2:20): [#ffff44] Humne har dard ko ashaar mein dhala aakhir, tab gazal mein bhara bhar rehta hai.",
                "(2:41 - 2:58): [#ff44ff] Humne duniya ki chamak dekh ke jaana aakhir, dil ka sukoon hi sabse bada rehta hai.",
                "(3:02 - 3:13): [#00ccff] Dil ka sukoon hi sabse bada rehta hai, phool khushboo se juda ho nahi sakte hargiz.",
                "(3:20 - 3:31): [#ffaa44] Ishq ki rag mein wafa banke rawa rehta hai.",
                "(3:41 - 4:00): [#cc44ff] Raat khamosh thi lekin mere andar har su, ek sada banke ummeedon ka diya rehta hai.",
                "(4:02 - 4:16): [#44ccff] Phool khushboo se juda ho nahi sakte hargiz.",
                "(4:20 - 4:34): [#ff4477] Ishq ki rag mein wafa banke rawa rehta hai.",
                "(4:41 - 4:47): [#aaaaaa] Humne har dard ko ashaar mein dhala aakhir, tab gazal mein bhara bhar rehta hai."
            ]
        }
    ]
}
